nuqql_matrixd_nio/__init__.py
nuqql_matrixd_nio/client.py
nuqql_matrixd_nio/main.py
nuqql_matrixd_nio/matrix.py
nuqql_matrixd_nio/server.py
nuqql_matrixd_nio-0.4.0.dist-info/LICENSE
nuqql_matrixd_nio-0.4.0.dist-info/METADATA
nuqql_matrixd_nio-0.4.0.dist-info/WHEEL
nuqql_matrixd_nio-0.4.0.dist-info/entry_points.txt
nuqql_matrixd_nio-0.4.0.dist-info/top_level.txt
nuqql_matrixd_nio-0.4.0.dist-info/RECORD
