Metadata-Version: 2.1
Name: nuqql-matrixd-nio
Version: 0.4.0
Summary: Matrix client network daemon using matrix-nio
Home-page: https://github.com/hwipl/nuqql-matrixd-nio
Author: hwipl
Author-email: nuqql-matrixd@hwipl.net
License: MIT
Classifier: Programming Language :: Python :: 3
Classifier: License :: OSI Approved :: MIT License
Requires-Python: >=3.7
License-File: LICENSE
Requires-Dist: nuqql-based~=0.3.0
Requires-Dist: matrix-nio[e2e]~=0.25.2
